germanium/__init__.py
germanium/config.py
germanium/crawler.py
germanium/decorators.py
germanium/patch.py
germanium/signals.py
germanium/storage.py
germanium/sugar.py
germanium/django/__init__.py
germanium/django/runner.py
germanium/django/utils.py
germanium/test_cases/__init__.py
germanium/test_cases/auth.py
germanium/test_cases/client.py
germanium/test_cases/default.py
germanium/test_cases/migrations.py
germanium/test_cases/models.py
germanium/test_cases/rest.py
germanium/tools/__init__.py
germanium/tools/django.py
germanium/tools/http.py
germanium/tools/models.py
germanium/tools/rest.py
germanium/tools/trivials.py
skip_django_germanium-2.6.0.dist-info/licenses/LICENSE
skip_django_germanium-2.6.0.dist-info/METADATA
skip_django_germanium-2.6.0.dist-info/WHEEL
skip_django_germanium-2.6.0.dist-info/top_level.txt
skip_django_germanium-2.6.0.dist-info/RECORD
