Metadata-Version: 2.4
Name: skip-django-germanium
Version: 2.6.0
Summary: Helpful methods for Python Selenium and REST testing
Home-page: https://github.com/skip-pay/germanium
Author: Lukas Rychtecky, Lubos Matl
Author-email: lukas.rychtecky@gmail.com, matllubos@gmail.com
Classifier: Development Status :: 3 - Alpha
Classifier: Intended Audience :: Developers
Classifier: License :: OSI Approved :: MIT License
Classifier: Operating System :: OS Independent
Classifier: Programming Language :: Python
License-File: LICENSE
Requires-Dist: django>=4.2
Requires-Dist: PyVirtualDisplay>=0.1.2
Requires-Dist: selenium>=2.37.2
Requires-Dist: pynose>=1.5.4
Requires-Dist: responses>=0.5.1
Dynamic: author
Dynamic: author-email
Dynamic: classifier
Dynamic: home-page
Dynamic: license-file
Dynamic: requires-dist
Dynamic: summary
